Workbook
Name Distritos_1: 'Distritos'!$B$2:$B$13
Name Distritos_10: 'Distritos'!$B$164:$B$176
Name Distritos_11: 'Distritos'!$B$177:$B$199
Name Distritos_12: 'Distritos'!$B$200:$B$219
Name Distritos_13: 'Distritos'!$B$220:$B$245
Name Distritos_14: 'Distritos'!$B$246:$B$263
Name Distritos_2: 'Distritos'!$B$14:$B$26
Name Distritos_3: 'Distritos'!$B$27:$B$42
Name Distritos_4: 'Distritos'!$B$43:$B$75
Name Distritos_5: 'Distritos'!$B$76:$B$97
Name Distritos_6: 'Distritos'!$B$98:$B$116
Name Distritos_7: 'Distritos'!$B$117:$B$132
Name Distritos_8: 'Distritos'!$B$133:$B$154
Name Distritos_9: 'Distritos'!$B$155:$B$163
Name Municipios_0: 'Municipios'!$B$46:$B$46
Name Municipios_1: 'Municipios'!$B$2:$B$4
Name Municipios_10: 'Municipios'!$B$34:$B$35
Name Municipios_11: 'Municipios'!$B$36:$B$38
Name Municipios_12: 'Municipios'!$B$39:$B$41
Name Municipios_13: 'Municipios'!$B$42:$B$43
Name Municipios_14: 'Municipios'!$B$44:$B$45
Name Municipios_2: 'Municipios'!$B$5:$B$8
Name Municipios_3: 'Municipios'!$B$9:$B$12
Name Municipios_4: 'Municipios'!$B$13:$B$15
Name Municipios_5: 'Municipios'!$B$16:$B$21
Name Municipios_6: 'Municipios'!$B$22:$B$26
Name Municipios_9: 'Municipios'!$B$32:$B$33
Name Municipios_7: 'Municipios'!$B$27:$B$28
Name Municipios_8: 'Municipios'!$B$29:$B$31

Sheet clientes
A1: nombre_empresa | B1: ncr | C1: giro | D1: cod_giro | E1: tipo_contribuyente | F1: dui | G1: nit | H1: direccion | I1: departamento | J1: cod_departamento | K1: distrito | L1: cod_distrito | M1: municipio | N1: cod_municipio | O1: telefono | P1: correo
A2: Empresa de ejemplo S.A. de C.V. | B2: 12345678901234 | C2: Acabado de productos textiles | D2: =IF(C2<>"",INDEX(Actividades!A:A,MATCH(C2,Actividades!B:B,0)),"") -> 13130 | E2: Otro | G2: 06140101000000 | H2: Colonia Ejemplo, Calle Principal #123, San Salvador | I2: San Salvador | J2: =IF(I2<>"",INDEX(Departamentos!A:A,MATCH(I2,Departamentos!B:B,0)),"") -> 6 | K2: SAN SALVADOR | L2: =IF(K2<>"",INDEX(Distritos!A:A,MATCH(K2,Distritos!B:B,0)),"") -> 14 | M2: SAN SALVADOR CENTRO | N2: =IF(M2<>"",INDEX(Municipios!A:A,MATCH(M2,Municipios!B:B,0)),"") -> 23 | O2: 22223333 | P2: correoejemplo@ejemplo.com
D3: =IF(C3<>"",INDEX(Actividades!A:A,MATCH(C3,Actividades!B:B,0)),"") | J3: =IF(I3<>"",INDEX(Departamentos!A:A,MATCH(I3,Departamentos!B:B,0)),"") | L3: =IF(K3<>"",INDEX(Distritos!A:A,MATCH(K3,Distritos!B:B,0)),"") | N3: =IF(M3<>"",INDEX(Municipios!A:A,MATCH(M3,Municipios!B:B,0)),"")
D4: =IF(C4<>"",INDEX(Actividades!A:A,MATCH(C4,Actividades!B:B,0)),"") | J4: =IF(I4<>"",INDEX(Departamentos!A:A,MATCH(I4,Departamentos!B:B,0)),"") | L4: =IF(K4<>"",INDEX(Distritos!A:A,MATCH(K4,Distritos!B:B,0)),"") | N4: =IF(M4<>"",INDEX(Municipios!A:A,MATCH(M4,Municipios!B:B,0)),"")
D5: =IF(C5<>"",INDEX(Actividades!A:A,MATCH(C5,Actividades!B:B,0)),"") | J5: =IF(I5<>"",INDEX(Departamentos!A:A,MATCH(I5,Departamentos!B:B,0)),"") | L5: =IF(K5<>"",INDEX(Distritos!A:A,MATCH(K5,Distritos!B:B,0)),"") | N5: =IF(M5<>"",INDEX(Municipios!A:A,MATCH(M5,Municipios!B:B,0)),"")
D6: =IF(C6<>"",INDEX(Actividades!A:A,MATCH(C6,Actividades!B:B,0)),"") | J6: =IF(I6<>"",INDEX(Departamentos!A:A,MATCH(I6,Departamentos!B:B,0)),"") | L6: =IF(K6<>"",INDEX(Distritos!A:A,MATCH(K6,Distritos!B:B,0)),"") | N6: =IF(M6<>"",INDEX(Municipios!A:A,MATCH(M6,Municipios!B:B,0)),"")
D7: =IF(C7<>"",INDEX(Actividades!A:A,MATCH(C7,Actividades!B:B,0)),"") | J7: =IF(I7<>"",INDEX(Departamentos!A:A,MATCH(I7,Departamentos!B:B,0)),"") | L7: =IF(K7<>"",INDEX(Distritos!A:A,MATCH(K7,Distritos!B:B,0)),"") | N7: =IF(M7<>"",INDEX(Municipios!A:A,MATCH(M7,Municipios!B:B,0)),"")
D8: =IF(C8<>"",INDEX(Actividades!A:A,MATCH(C8,Actividades!B:B,0)),"") | J8: =IF(I8<>"",INDEX(Departamentos!A:A,MATCH(I8,Departamentos!B:B,0)),"") | L8: =IF(K8<>"",INDEX(Distritos!A:A,MATCH(K8,Distritos!B:B,0)),"") | N8: =IF(M8<>"",INDEX(Municipios!A:A,MATCH(M8,Municipios!B:B,0)),"")
D9: =IF(C9<>"",INDEX(Actividades!A:A,MATCH(C9,Actividades!B:B,0)),"") | J9: =IF(I9<>"",INDEX(Departamentos!A:A,MATCH(I9,Departamentos!B:B,0)),"") | L9: =IF(K9<>"",INDEX(Distritos!A:A,MATCH(K9,Distritos!B:B,0)),"") | N9: =IF(M9<>"",INDEX(Municipios!A:A,MATCH(M9,Municipios!B:B,0)),"")
D10: =IF(C10<>"",INDEX(Actividades!A:A,MATCH(C10,Actividades!B:B,0)),"") | J10: =IF(I10<>"",INDEX(Departamentos!A:A,MATCH(I10,Departamentos!B:B,0)),"") | L10: =IF(K10<>"",INDEX(Distritos!A:A,MATCH(K10,Distritos!B:B,0)),"") | N10: =IF(M10<>"",INDEX(Municipios!A:A,MATCH(M10,Municipios!B:B,0)),"")
D11: =IF(C11<>"",INDEX(Actividades!A:A,MATCH(C11,Actividades!B:B,0)),"") | J11: =IF(I11<>"",INDEX(Departamentos!A:A,MATCH(I11,Departamentos!B:B,0)),"") | L11: =IF(K11<>"",INDEX(Distritos!A:A,MATCH(K11,Distritos!B:B,0)),"") | N11: =IF(M11<>"",INDEX(Municipios!A:A,MATCH(M11,Municipios!B:B,0)),"")
D12: =IF(C12<>"",INDEX(Actividades!A:A,MATCH(C12,Actividades!B:B,0)),"") | J12: =IF(I12<>"",INDEX(Departamentos!A:A,MATCH(I12,Departamentos!B:B,0)),"") | L12: =IF(K12<>"",INDEX(Distritos!A:A,MATCH(K12,Distritos!B:B,0)),"") | N12: =IF(M12<>"",INDEX(Municipios!A:A,MATCH(M12,Municipios!B:B,0)),"")
D13: =IF(C13<>"",INDEX(Actividades!A:A,MATCH(C13,Actividades!B:B,0)),"") | J13: =IF(I13<>"",INDEX(Departamentos!A:A,MATCH(I13,Departamentos!B:B,0)),"") | L13: =IF(K13<>"",INDEX(Distritos!A:A,MATCH(K13,Distritos!B:B,0)),"") | N13: =IF(M13<>"",INDEX(Municipios!A:A,MATCH(M13,Municipios!B:B,0)),"")
D14: =IF(C14<>"",INDEX(Actividades!A:A,MATCH(C14,Actividades!B:B,0)),"") | J14: =IF(I14<>"",INDEX(Departamentos!A:A,MATCH(I14,Departamentos!B:B,0)),"") | L14: =IF(K14<>"",INDEX(Distritos!A:A,MATCH(K14,Distritos!B:B,0)),"") | N14: =IF(M14<>"",INDEX(Municipios!A:A,MATCH(M14,Municipios!B:B,0)),"")
... D1000: =IF(C1000<>"",INDEX(Actividades!A:A,MATCH(C1000,Actividades!B:B,0)),"") | J1000: =IF(I1000<>"",INDEX(Departamentos!A:A,MATCH(I1000,Departamentos!B:B,0)),"") | L1000: =IF(K1000<>"",INDEX(Distritos!A:A,MATCH(K1000,Distritos!B:B,0)),"") | N1000: =IF(M1000<>"",INDEX(Municipios!A:A,MATCH(M1000,Municipios!B:B,0)),"")

Sheet Instrucciones
A1: Importación de clientes tipo empresa (El Salvador)
A3: 1. Complete únicamente la hoja «clientes». Las demás son catálogos para las fórmulas de códigos (cod_giro, cod_departamento, etc.).
A4: 2. nombre_empresa y NCR son obligatorios.
A5: 3. Distrito (K) y municipio (M) tienen listas con todo el catálogo (como departamento): puede buscar y elegir cualquier fila. Conviene que coincida con el departamento (I) para que los códigos J, L y N sean coherentes.
A6: 4. La fila 2 es un ejemplo; desde la fila 3 tiene las mismas fórmulas y listas para agregar más clientes.
A7: 5. No elimine ni mueva las pestañas de catálogo (Actividades, Departamentos, Distritos, Municipios) si usa listas o fórmulas.
A8: 6. Solo se importa la primera hoja del archivo; debe llamarse «clientes» y ser la primera pestaña (izquierda).
A9: 7. nit y teléfono: use formato texto en Excel cuando haga falta para no perder ceros.
A10: 8. correo es opcional; «-» o vacío se aceptan.

Sheet tipo_contribuyente
A1: Pequeño
A2: Mediano
A3: Grande
A4: Otro

Sheet Departamentos
A1: cod_departamento | B1: departamento
A2: 1 | B2: Ahuachapán
A3: 2 | B3: Santa Ana
A4: 3 | B4: Sonsonate
A5: 4 | B5: Chalatenango
A6: 5 | B6: La Libertad
A7: 6 | B7: San Salvador
A8: 7 | B8: Cuscatlán
A9: 8 | B9: La Paz
A10: 9 | B10: Cabañas
A11: 10 | B11: San Vicente
A12: 11 | B12: Usulután
A13: 12 | B13: San Miguel
... A16: 0 | B16: Otro

Sheet Municipios
A1: cod | B1: nombre | C1: cod_departamento
A2: 13 | B2: AHUACHAPÁN NORTE | C2: 1
A3: 14 | B3: AHUACHAPÁN CENTRO | C3: 1
A4: 15 | B4: AHUACHAPÁN SUR | C4: 1
A5: 14 | B5: SANTA ANA NORTE | C5: 2
A6: 15 | B6: SANTA ANA CENTRO | C6: 2
A7: 16 | B7: SANTA ANA ESTE | C7: 2
A8: 17 | B8: SANTA ANA OESTE | C8: 2
A9: 17 | B9: SONSONATE NORTE | C9: 3
A10: 18 | B10: SONSONATE CENTRO | C10: 3
A11: 19 | B11: SONSONATE ESTE | C11: 3
A12: 20 | B12: SONSONATE OESTE | C12: 3
A13: 34 | B13: CHALATENANGO NORTE | C13: 4
... A46: 0 | B46: Otro | C46: 0

Sheet Distritos
A1: cod | B1: nombre | C1: cod_municipio | D1: cod_departamento
A2: 3 | B2: ATIQUIZAYA | C2: 13 | D2: 1
A3: 5 | B3: EL REFUGIO | C3: 13 | D3: 1
A4: 9 | B4: SAN LORENZO | C4: 13 | D4: 1
A5: 12 | B5: TURÍN | C5: 13 | D5: 1
A6: 1 | B6: AHUACHAPÁN | C6: 14 | D6: 1
A7: 2 | B7: APANECA | C7: 14 | D7: 1
A8: 4 | B8: CONCEPCIÓN DE ATACO | C8: 14 | D8: 1
A9: 11 | B9: TACUBA | C9: 14 | D9: 1
A10: 6 | B10: GUAYMANGO | C10: 15 | D10: 1
A11: 7 | B11: JUJUTLA | C11: 15 | D11: 1
A12: 8 | B12: SAN FRANCISCO MENÉNDEZ | C12: 15 | D12: 1
A13: 10 | B13: SAN PEDRO PUXTLA | C13: 15 | D13: 1
... A263: 18 | B263: YUCUAIQUÍN | C263: 20 | D263: 14

Sheet Actividades
A1: codigo | B1: nombre
A2: 13130 | B2: Acabado de productos textiles
A3: 97000 | B3: Actividad de los hogares en calidad de empleadores de personal doméstico
A4: 66190 | B4: Actividades auxiliares de la intermediación financiera ncp
A5: 66120 | B5: Actividades bursátiles (Corredores de Bolsa)
A6: 81100 | B6: Actividades combinadas de mantenimiento de edificios e instalaciones
A7: 90000 | B7: Actividades creativas artísticas y de esparcimiento
A8: 66300 | B8: Actividades de administración de fondos
A9: 84210 | B9: Actividades de administración y funcionamiento del Ministerio de Relaciones Exteriores
A10: 82910 | B10: Actividades de agencias de cobro y oficinas de crédito
A11: 79110 | B11: Actividades de agencias de viajes y organizadores de viajes; actividades de asistencia a turistas
A12: 66220 | B12: Actividades de agentes y corredores de seguros
A13: 55101 | B13: Actividades de alojamiento para estancias cortas
... A774: 46633 | B774: Vidrierías
